bids_like/__init__.py
bids_like-0.5.0.dist-info/METADATA
bids_like-0.5.0.dist-info/WHEEL
bids_like-0.5.0.dist-info/top_level.txt
bids_like-0.5.0.dist-info/RECORD
