Metadata-Version: 2.1
Name: bids-like
Version: 0.5.0
Summary: A lightweight Python library for handling BIDS-like datasets. They do not need to strictly follow the BIDS specification, but they should have a similar folder and file structure. All valid BIDS datasets are valid BIDS-like datasets.
Author-email: M Pabst <your.email@example.com>
Requires-Python: >=3.8
